shelved_cache/__init__.py
shelved_cache/decorators.py
shelved_cache/keys.py
shelved_cache/persistent_cache.py
shelved_cache_fixed-0.3.1.dist-info/LICENSE
shelved_cache_fixed-0.3.1.dist-info/METADATA
shelved_cache_fixed-0.3.1.dist-info/WHEEL
shelved_cache_fixed-0.3.1.dist-info/RECORD
