Metadata-Version: 2.1
Name: shelved_cache_fixed
Version: 0.3.1
Summary: Persistent cache for Python cachetools with fixes to major issues.
Home-page: https://github.com/uninstall-your-browser/shelved_cache
License: MIT
Author: Marius Helf
Author-email: helfsmarius@gmail.com
Requires-Python: >=3.7.0,<4.0.0
Classifier: Development Status :: 4 - Beta
Classifier: License :: OSI Approved :: MIT License
Classifier: Programming Language :: Python :: 3
Classifier: Programming Language :: Python :: 3.7
Classifier: Programming Language :: Python :: 3.8
Classifier: Programming Language :: Python :: 3.9
Classifier: Programming Language :: Python :: 3.10
Classifier: Programming Language :: Python :: 3.11
Classifier: Programming Language :: Python :: 3.12
Classifier: Programming Language :: Python :: Implementation :: PyPy
Requires-Dist: cachetools (>=4.2.2,<6.0.0)
Project-URL: Documentation, https://github.com/uninstall-your-browser/shelved_cache
Project-URL: Repository, https://github.com/uninstall-your-browser/shelved_cache
